<templateSet group="chenggongzhao">
  <template name="cmt" value="/**&#10;* $desc$&#10;*@author cgz&#10;*@version at $date$ $time$&#10;*/&#10;&#10;" description="方法注释模版" toReformat="false" toShortenFQNames="true">
    <variable name="desc" expression="" defaultValue="" alwaysStopAt="true" />
    <variable name="date" expression="date()" defaultValue="" alwaysStopAt="true" />
    <variable name="time" expression="time()" defaultValue="" alwaysStopAt="true" />
    <context>
      <option name="JAVA_CODE" value="true" />
    </context>
  </template>
</templateSet>